mhi/__init__.py
mhi/main.py
mhi/readlisp.py
mhi/sexpr.py
mhi/mklinks/__init__.py
mhi/mklinks/__main__.py
mhi-0.8.6.dist-info/LICENSE
mhi-0.8.6.dist-info/METADATA
mhi-0.8.6.dist-info/WHEEL
mhi-0.8.6.dist-info/entry_points.txt
mhi-0.8.6.dist-info/top_level.txt
mhi-0.8.6.dist-info/RECORD
