Metadata-Version: 2.1
Name: mhi
Version: 0.8.6
Summary: MH for IMAP
Author-email: Paul Jimenez <pj@place.org>
License: The code in this repository is released under GPLv3, described below,
Project-URL: Homepage, http://github.com/pjz/mhi
Project-URL: Repository, http://github.com/pjz/mhi.git
Classifier: Development Status :: 5 - Production/Stable
Classifier: Environment :: Console
Classifier: Intended Audience :: Developers
Classifier: Intended Audience :: End Users/Desktop
Classifier: Intended Audience :: System Administrators
Classifier: License :: OSI Approved :: GNU General Public License v3 or later (GPLv3+)
Classifier: Natural Language :: English
Classifier: Operating System :: MacOS :: MacOS X
Classifier: Operating System :: Microsoft :: Windows
Classifier: Operating System :: POSIX
Classifier: Programming Language :: Python :: 3.8
Classifier: Programming Language :: Python :: Implementation :: CPython
Classifier: Topic :: Communications :: Email :: Email Clients (MUA)
Requires-Python: >=3.8
License-File: LICENSE
Requires-Dist: configobj
Provides-Extra: dev
Requires-Dist: mock ; extra == 'dev'
Requires-Dist: twine ; extra == 'dev'
Requires-Dist: pytest ; extra == 'dev'
Requires-Dist: pytest-cov ; extra == 'dev'
Requires-Dist: pytest-mypy ; extra == 'dev'
Requires-Dist: pytest-pylint ; extra == 'dev'
Requires-Dist: pytest-timeout ; extra == 'dev'
Requires-Dist: pytest-runfailed ; extra == 'dev'
